cloudops/__init__.py
cloudops/secret_manager/__init__.py
cloudops/secret_manager/aws/__init__.py
cloudops/secret_manager/aws/secret.py
cloudops_secret_manager_aws-0.1.0.dist-info/METADATA
cloudops_secret_manager_aws-0.1.0.dist-info/WHEEL
cloudops_secret_manager_aws-0.1.0.dist-info/RECORD
