Metadata-Version: 2.1
Name: cloudops-secret-manager-aws
Version: 0.1.0
Summary: The cloudops-secret-manager-aws package
Home-page: https://github.com/manucalop/cloudops-secret-manager-aws
License: MIT
Author: Manuel Castillo
Author-email: manucalop@gmail.com
Requires-Python: >=3.9,<4.0
Classifier: License :: OSI Approved :: MIT License
Classifier: Programming Language :: Python :: 3
Classifier: Programming Language :: Python :: 3.9
Classifier: Programming Language :: Python :: 3.10
Classifier: Programming Language :: Python :: 3.11
Requires-Dist: boto3 (>=1.26.37,<2.0.0)
Requires-Dist: pydantic (>=1.10.2,<2.0.0)
Project-URL: Repository, https://github.com/manucalop/cloudops-secret-manager-aws
